MANIFEST.in
setup.py
src/kengste/__init__.py
src/kengste.egg-info/PKG-INFO
src/kengste.egg-info/SOURCES.txt
src/kengste.egg-info/dependency_links.txt
src/kengste.egg-info/top_level.txt
src/kengste.egg-info/zip-safe
src/kengste/hello/__init__.py
src/kengste/hello/main/Class1.py
src/kengste/hello/main/__init__.py
src/kengste/hello/main/main.py