Metadata-Version: 1.1
Name: kengste
Version: 0.0.5
Summary: Trying for fun
Home-page: UNKNOWN
Author: UNKNOWN
Author-email: UNKNOWN
License: UNKNOWN
Platform: UNKNOWN
Classifier: Intended Audience :: Developers
Classifier: Programming Language :: Python
